git_project/__init__.py
git_project/commandline.py
git_project/configobj.py
git_project/exception.py
git_project/git.py
git_project/gitproject.py
git_project/main.py
git_project/parsermanager.py
git_project/plugin.py
git_project/pluginmanager.py
git_project/project.py
git_project/runnable.py
git_project/scopedobj.py
git_project/shell.py
git_project/substitutable.py
git_project/test_support/__init__.py
git_project/test_support/common.py
git_project-0.0.28.dist-info/METADATA
git_project-0.0.28.dist-info/WHEEL
git_project-0.0.28.dist-info/entry_points.txt
git_project-0.0.28.dist-info/licenses/COPYING
git_project-0.0.28.dist-info/RECORD
