Metadata-Version: 2.4
Name: git-project
Version: 0.0.28
Summary: The extensible stupid project manager
Author-email: "David A. Greene" <dag@obbligato.org>
License-Expression: AGPL-3.0-or-later
License-File: COPYING
Keywords: development,git,project
Classifier: Development Status :: 3 - Alpha
Classifier: Environment :: Console
Classifier: Intended Audience :: Developers
Classifier: License :: OSI Approved :: GNU Affero General Public License v3 or later (AGPLv3+)
Classifier: Programming Language :: Python :: 3.9
Classifier: Topic :: Software Development :: Version Control :: Git
Requires-Python: >=3.9
Requires-Dist: progressbar2>=4.4.2
Requires-Dist: pygit2>=1.15.1
Provides-Extra: test
Requires-Dist: pytest; extra == 'test'
Requires-Dist: pytest-console-scripts; extra == 'test'
Requires-Dist: pytest-cov; extra == 'test'
Requires-Dist: setuptools; extra == 'test'
